{
  "cards": [
    {
      "word": "אמר",
      "definition": {}
    },
    {
      "word": "דבר",
      "definition": {}
    },
    {
      "word": "עשה",
      "definition": {}
    },
    {
      "word": "ראה",
      "definition": {}
    },
    {
      "word": "שמע",
      "definition": {}
    },
    {
      "word": "הלך",
      "definition": {}
    },
    {
      "word": "בא",
      "definition": {}
    },
    {
      "word": "נתן",
      "definition": {}
    },
    {
      "word": "לקח",
      "definition": {}
    },
    {
      "word": "אמרו",
      "definition": {}
    }
  ]
}